MANIFEST.in
README.md
requirements.txt
setup.py
djparsing/__init__.py
djparsing/core.py
djparsing/data.py
djparsing/exceptions.py
djparsing/options.py
djparsing/parser.py
djparsing/settings.py
djparsing/test.py
djparsing.egg-info/PKG-INFO
djparsing.egg-info/SOURCES.txt
djparsing.egg-info/dependency_links.txt
djparsing.egg-info/requires.txt
djparsing.egg-info/top_level.txt