Metadata-Version: 1.1
Name: djparsing
Version: 0.2.7
Summary: microframework for parsing sites, a simple interface and flexibility will help you quickly start parsing sites.Convenient parsing, can be used as an application Django or independently
Home-page: https://github.com/lincvv/djparsing
Author: lincvv
Author-email: vlinchevskyi@gmail.com
License: BSD License
Platform: UNKNOWN
Classifier: Environment :: Web Environment
Classifier: Framework :: Django
Classifier: Intended Audience :: Developers
Classifier: License :: OSI Approved :: BSD License
Classifier: Operating System :: OS Independent
Classifier: Programming Language :: Python
Classifier: Programming Language :: Python :: 3.4
Classifier: Programming Language :: Python :: 3.5
Classifier: Programming Language :: Python :: 3.6
Classifier: Topic :: Utilities
